{"word": "alias", "headword": "alias", "frequency": "155", "list": "10k", "usPhone": "ˈeɪliəs", "ukPhone": "ˈeɪliəs", "examType": ["SAT"], "translations": ["adv.又名，化名（尤指演员或罪犯）", "n.（尤指罪犯所用的）化名，别名；（文件、互联网地址等用的）别名，假名；假频伪信号", "v.错误识别（信号频率），使失真", "【名】 （Alias）（马、美、英、印）阿利亚（人名）"], "phrs": [{"headword": "alias", "key-speech": "alias", "translation": "别名, 小应用程序, 设置命令别名, 特工风云"}, {"headword": "Anti-Alias Crisp", "key-speech": "Anti-Alias+Crisp", "translation": "消除锯齿明晰, 清除锯齿清晰, 消除锯齿清晰"}, {"headword": "Anti-Alias Strong", "key-speech": "Anti-Alias+Strong", "translation": "消除锯齿强"}, {"headword": "Anti-Alias None", "key-speech": "Anti-Alias+None", "translation": "清除锯齿无, 排除锯齿无, 打消锯齿无"}, {"headword": "Anti-Alias", "key-speech": "Anti-Alias", "translation": "反锯齿, 消锯齿, 抗锯齿"}, {"headword": "Alias Crisp", "key-speech": "Alias+Crisp", "translation": "消除锯齿明晰"}, {"headword": "Alias scorpion", "key-speech": "Alias+scorpion", "translation": "双面女蝎"}, {"headword": "alias section", "key-speech": "alias+section", "translation": "别名段, 别名区段"}, {"headword": "Alias Grace", "key-speech": "Alias+Grace", "translation": "别名格蕾丝, 别名格雷斯, 双面葛蕾斯, 双面格蕾丝"}, {"headword": "Database Alias", "key-speech": "Database+Alias", "translation": "数据库别名, 称为数据库别号"}], "sentences": [{"sentence": "He checked into the hotel under an alias.", "translation": "他用化名登记住进旅馆。"}, {"sentence": "Using an alias, he had rented a house in Des Moines.", "translation": "通过使用一个化名，他已在得梅因租了一所房子。"}, {"sentence": "Richard Thorp, alias Alan Turner, said yesterday: \"It is a sad time for both of us.\"", "translation": "理查德·索普，又名为阿伦·特纳，昨天说道：“这对我们两个人来说都是一个悲伤的时刻”。"}]}