{"word": "antitheses", "headword": "thesis", "frequency": "13", "list": "4k", "usPhone": "", "ukPhone": "ænˈtɪθɪsiːz", "examType": [], "translations": ["n.对比法；对照"], "phrs": [{"headword": "antitheses", "key-speech": "antitheses", "translation": "对立的, 对照, 对比论, 正相反"}, {"headword": "antitheses antithesis", "key-speech": "antitheses+antithesis", "translation": "的复数"}, {"headword": "A Brief Account on ANTITHESES", "key-speech": "A+Brief+Account+on+ANTITHESES", "translation": "浅谈对偶"}, {"headword": "antitheses group", "key-speech": "antitheses+group", "translation": "对照组"}, {"headword": "antitheses design", "key-speech": "antitheses+design", "translation": "对偶性概念"}, {"headword": "antitheses test", "key-speech": "antitheses+test", "translation": "比对试验"}, {"headword": "ambipolar antitheses", "key-speech": "ambipolar+antitheses", "translation": "二极对偶"}, {"headword": "special antitheses", "key-speech": "special+antitheses", "translation": "特殊反衬"}, {"headword": "antitheses s antithesis", "key-speech": "antitheses+s+antithesis", "translation": "的复数"}, {"headword": "Standard Area Antitheses", "key-speech": "Standard+Area+Antitheses", "translation": "标准区域类比法"}], "sentences": [{"sentence": "There are many antitheses in this poem.", "translation": "这首诗里含有大量的流水对。"}, {"sentence": "Benefit computation can be used commonly have, antitheses.", "translation": "效益计算一般可采用有、无对比法。"}, {"sentence": "Another 30 normal people were chosen for the antitheses group and were also given the above measured indexes.", "translation": "另选30例健康人作为对照组进行上述指标的测量。"}]}