{"word": "barky", "headword": "barky", "frequency": "8", "list": "22k", "usPhone": "ˈbɑːrki", "ukPhone": "ˈbɑːkɪ", "examType": [], "translations": ["adj.[植] 含有树皮的；似树皮的"], "phrs": [{"headword": "barky", "key-speech": "barky", "translation": "树皮的, 有树皮的, 含有树皮的, 巴基"}, {"headword": "Barky par", "key-speech": "Barky+par", "translation": "特别附加赛"}, {"headword": "barky zori", "key-speech": "barky+zori", "translation": "多带式凉鞋"}, {"headword": "Cork Barky", "key-speech": "Cork+Barky", "translation": "栓皮病"}], "sentences": []}