{"word": "bejewelled", "headword": "bejewelled", "frequency": "29", "list": "19k", "usPhone": "bɪˈdʒuːəld", "ukPhone": "bɪˈdʒuːəld", "translations": ["饰以珠宝的（bejewel 的变体）"], "phrs": [], "sentences": [{"sentence": "The proceeds from the sale of the bejewelled Barbie will go to Breast Cancer Research.", "translation": "这件珠宝芭比娃娃拍卖所得的利润将会捐赠乳腺癌研究。"}, {"sentence": "In Egypt magazines such as Hijab Fashion have proliferated, along with shops selling bejewelled and beribboned scarves.", "translation": "在埃及，“头巾时尚”等杂志风行；有些商店出售饰有珠宝与丝带的头巾，如雨后春笋般出现。"}, {"sentence": "\"Baroque: Style in the Age of Magnificence\" begins with a captivating bejewelled camel (pictured below) with \"blackamoor\" attendants.", "translation": "一尊镶有珠宝的精美骆驼(其图如下)将拉开“巴洛克：辉煌时代的风格”的序幕，此尊骆驼旁还雕刻着一个“黑人”解说员。"}]}