{"word": "biff", "headword": "biff", "frequency": "193", "list": "14k", "usPhone": "bɪf", "ukPhone": "bɪf", "translations": ["（用拳头）狠打；（非正式，骑单车等时）摔下来", "（用拳的）重击；洋相；（Biff）比夫（人名）"], "phrs": [], "sentences": [{"sentence": "One character, Biff, could never hold down a job.", "translation": "其中的一个角色，比夫，总是不能保住工作。"}, {"sentence": "Always sign with your (entire) real name, not some wacky nickname like Ry-Ry or Biff.", "translation": "一定要签上你的真实姓名（全名），而不是 Ry-Ry 或 Biff 这样的古怪昵称。"}, {"sentence": "My employee, Biff, has been late to work the past three days; I notice this and conclude that Biff is lazy and does not care about his job.", "translation": "我的员工比夫过去三天上班老是迟到；我注意到了这一点，得出结论：比夫很懒，不关心自己的工作。"}]}