{"word": "burials", "headword": "bury", "frequency": "143", "list": "2k", "usPhone": "", "ukPhone": "", "examType": ["CET4", "CET6", "GRE"], "translations": ["n．埋葬，葬礼（burial的复数形式）：将死者遗体安置在墓地或其他指定地点的仪式。", "· The archaeologists discovered several ancient burials at the site.", "考古学家在这个遗址发现了几处古代墓葬。"], "phrs": [{"headword": "burial depth", "translation": "埋深，埋藏深度"}, {"headword": "burial ground", "translation": "坟地；废物埋藏场"}], "sentences": [{"sentence": "As expected, vanadium was found in considerably greater quantities in skeletons in the burials of lower-status groups.", "translation": "正如预期的那样，在较低地位群体墓葬的骨骼中发现的钒要多得多。"}, {"sentence": "These burials included quantities of finely carried items made of nonlocal material, denoting the high political standing of those interred.", "translation": "这些墓葬包括大量由外地材料制成的精细搬运物品，表明了被埋葬者的高度政治地位。"}, {"sentence": "The burials actually formed a pattern, the tallest skeletons being found in the mounds, and the heights declining as burials became more distant from the mounds.", "translation": "墓葬实际上形成了一种模式，在土堆中发现了最高的骨架，随着墓葬距离土堆越远，其高度就越低。"}]}