{"word": "cementing", "headword": "cement", "frequency": "44", "list": "5k", "usPhone": "sɪˈmentɪŋ", "ukPhone": "", "examType": ["CET4", "CET6", "考研", "TOEFL", "GRE", "商务英语"], "translations": ["n.胶接；粘合；凝结", "v.用水泥涂（cement 的现在分词）"], "phrs": [{"headword": "cementing material", "translation": "胶凝材料；胶结料，粘合剂"}, {"headword": "cementing agent", "translation": "胶接剂；粘合剂"}], "sentences": [{"sentence": "Cementing material can also be extracted from lunar resources.", "translation": "胶结物也可以从月球资源中提取。"}, {"sentence": "The cabinet changes seemed aimed at cementing his own authority.", "translation": "改组内阁的目的似乎在于稳固自己的权威。"}, {"sentence": "Then there is the cementing of the wellhead, a process which is necessarily tricky.", "translation": "接着是油井井口的水泥灌浆，这是一项相当棘手的任务。"}]}