{"word": "chroma", "headword": "chroma", "frequency": "2", "list": "23k", "usPhone": "ˈkroʊmə", "ukPhone": "ˈkrəʊmə", "examType": [], "translations": ["n.（色彩的）浓度，[光] 色度"], "phrs": [{"headword": "chroma", "key-speech": "chroma", "translation": "彩度, 透明色, 色度, 致茂电子"}, {"headword": "chroma key", "key-speech": "chroma+key", "translation": "色键, 色度键, 色键抠像, 色度镶迭法"}, {"headword": "chroma subsampling", "key-speech": "chroma+subsampling", "translation": "色度抽样"}, {"headword": "CHROMA GAIN", "key-speech": "CHROMA+GAIN", "translation": "色度增益"}, {"headword": "CHROMA TRAP FO", "key-speech": "CHROMA+TRAP+FO", "translation": "色度信号陷波频率, 色度旌旗灯号陷波频率"}, {"headword": "Chroma-Ways", "key-speech": "Chroma-Ways", "translation": "彩石之路"}, {"headword": "Chroma compensator", "key-speech": "Chroma+compensator", "translation": "色度补偿器, 色度弥补器"}, {"headword": "CHROMA TRAP", "key-speech": "CHROMA+TRAP", "translation": "色度信号陷波Q值, 色度旌旗灯号陷波Q值"}, {"headword": "Chroma Squad", "key-speech": "Chroma+Squad", "translation": "彩度战队, 五彩小队, 五彩战队, 五色战队"}, {"headword": "Automatic Chroma Control", "key-speech": "Automatic+Chroma+Control", "translation": "自动色度, 自动色度控制"}], "sentences": [{"sentence": "The chroma interpolation along edges produces noticeable haloing artifacts.", "translation": "沿边缘的色度插值会产生明显的光晕伪像。"}, {"sentence": "Chroma prediction modes are practically identical as well.", "translation": "色度预测模式也几乎相同。"}, {"sentence": "Blue and green are the chroma key colors most frequently used.", "translation": "使用得最多最频繁的色键颜色是蓝色和绿色。"}]}