{"word": "coheres", "headword": "coherent", "frequency": "6", "list": "4k", "usPhone": "", "ukPhone": "", "translations": ["共同继续人（cohere 复数）", "一致（cohere 的三单形式）"], "phrs": [{"headword": "cohere with", "translation": "符合"}], "sentences": [{"sentence": "There are moral principles by which society coheres.", "translation": "有些道德法则使社会得以团结一致。"}, {"sentence": "That coheres with philosophy of Daoism and Chan Buddhism.", "translation": "这恰恰回到了道家的哲学和禅学境界里来了。"}, {"sentence": "Pricing evolves as a startup 's product matures, its brand solidifies and its team coheres.", "translation": "定价随着创业公司产品日趋成熟、品牌和团队不断强化而演变。"}]}