{"word": "crestfallen", "headword": "crestfallen", "frequency": "43", "list": "14k", "usPhone": "ˈkrestfɔːlən", "ukPhone": "ˈkrestfɔːlən", "examType": ["GRE", "SAT"], "translations": ["adj.垂头丧气的，气馁的"], "phrs": [{"headword": "Crestfallen", "key-speech": "Crestfallen", "translation": "灰溜溜, 垂头丧气, 挫败的, 意气沮丧的"}, {"headword": "crestfallen exultant", "key-speech": "crestfallen+exultant", "translation": "垂头丧气的"}, {"headword": "Say a few words crestfallen", "key-speech": "Say+a+few+words+crestfallen", "translation": "说上几句垂头丧气的话"}, {"headword": "Return Crestfallen", "key-speech": "Return+Crestfallen", "translation": "败兴而归"}, {"headword": "Sounding Crestfallen", "key-speech": "Sounding+Crestfallen", "translation": "垂头丧气地"}, {"headword": "Somewhat Crestfallen", "key-speech": "Somewhat+Crestfallen", "translation": "有点垂头丧气"}, {"headword": "But Not Crestfallen", "key-speech": "But+Not+Crestfallen", "translation": "但没有垂头丧气"}, {"headword": "foolish and crestfallen", "key-speech": "foolish+and+crestfallen", "translation": "傻乎乎地目瞪口呆"}, {"headword": "She Looked Crestfallen", "key-speech": "She+Looked+Crestfallen", "translation": "她看上去垂头丧气"}], "sentences": [{"sentence": "\"He did it awfully well,\" said the crestfallen Rat.", "translation": "“他装得太好了。”水鼠垂头丧气地说。"}, {"sentence": "He gathered himself up and sneaked off, crushed and crestfallen.", "translation": "他爬起来，偷偷溜走了，他被压垮了，垂头丧气。"}, {"sentence": "Hamilton looks crestfallen.", "translation": "汉密尔顿看起来垂头丧气。"}]}