{"word": "doctors", "headword": "doctor", "frequency": "4459", "list": "1k", "usPhone": "ˈdɑːktərz", "ukPhone": "", "examType": ["初中", "高中", "CET4", "CET6", "考研"], "translations": ["n.[医]医生（doctor 的复数）", "v.为……诊治（doctor 的单数第三人称）"], "phrs": [{"headword": "women doctors", "translation": "女大夫；女医生们"}], "sentences": [{"sentence": "Doctors become inured to death.", "translation": "医生们对死亡变得习以为常。"}, {"sentence": "Doctors think he will go blind.", "translation": "医生们认为他会失明。"}, {"sentence": "Doctors certified him as insane.", "translation": "医生证明他精神失常。"}]}