{"word": "eagled", "headword": "eagle", "frequency": "28", "list": "4k", "usPhone": "", "ukPhone": "", "examType": ["高中", "CET4", "CET6", "考研"], "translations": ["vi.在一洞中比标准杆低两杆（eagle 的过去式和过去分词）"], "phrs": [{"headword": "bald eagle", "translation": "（美）秃鹰（美国的国鸟）；比喻秃头的政治家"}, {"headword": "golden eagle", "translation": "金雕"}, {"headword": "eagle eye", "translation": "鹰眼；敏锐的目光；目光锐利的人"}, {"headword": "screaming eagle", "translation": "鹰鸣酒（一种美国葡萄酒）"}, {"headword": "sea eagle", "translation": "海鹰；白尾海雕"}], "sentences": [{"sentence": "He had eagled the same hole earlier today.", "translation": "今天早些时候，他低于标准杆两杆进了同一个洞。"}, {"sentence": "Harry looked down and saw Hagrid spread-eagled on the ground below him.", "translation": "哈利低头一看，海格四仰八叉地躺在下面的地上。"}, {"sentence": "And she was giggling at him. Spread-eagled on the floor, her brocaded gown hitched up above her thighs, she taunted him between giggles.", "translation": "她朝他一个劲地格格地傻笑，她手脚伸展着躺在地板上，把花缎旗袍拉上来露出大腿。"}]}