{"word": "extenuation", "headword": "extenuate", "frequency": "2", "list": "15k", "usPhone": "ɪkˈstenjuˈeɪʃən", "ukPhone": "ɪksˈtenjʊˈeɪʃən", "examType": [], "translations": ["n.减轻；酌情减轻"], "phrs": [{"headword": "extenuation", "key-speech": "extenuation", "translation": "衰弱, 衷减, 酌情减轻"}, {"headword": "extenuation of a crime", "key-speech": "extenuation+of+a+crime", "translation": "减轻罪行, 翻译"}, {"headword": "elastic extenuation", "key-speech": "elastic+extenuation", "translation": "弹性衰减"}], "sentences": [{"sentence": "It was a comfort to him, this extenuation.", "translation": "这借口对他是种安慰。"}, {"sentence": "The lawyer pleaded his client's youth in extenuation of the crime.", "translation": "律师以其当事人年少为由请求减轻其罪行。"}, {"sentence": "The circumstances of his marriage, too, were found to admit of much extenuation.", "translation": "他们发现，他的婚姻情况也是十分情有可原的。"}]}