{"word": "externalised", "headword": "external", "frequency": "6", "list": "3k", "usPhone": "", "ukPhone": "", "examType": [], "translations": ["v.使……形象化，使外化；用言辞（或行动）表达；使（意象或心理过程）表面化；将（工作）外包（externalise 的过去式和过去分词）"], "phrs": [], "sentences": [{"sentence": "The key thing about these externalised interactions and behaviours is that they represent the business-meaningful stuff that must happen for some part of a business activity to proceed or complete.", "translation": "关于这些外部化的交互与行为，关键之处在于它们表示的是对业务有意义的东西，它们若不发生，业务活动的某部分就无法继续或完成。"}]}