{"word": "feminisation", "headword": "feminize", "frequency": "4", "list": "14k", "usPhone": "", "ukPhone": "", "examType": [], "translations": ["女性化", "雌性化"], "phrs": [{"headword": "feminisation in migration", "key-speech": "feminisation+in+migration", "translation": "化趋势"}, {"headword": "Feminisation of the stamens", "key-speech": "Feminisation+of+the+stamens", "translation": "雄蕊雌性化"}, {"headword": "testicular feminisation syndrome", "key-speech": "testicular+feminisation+syndrome", "translation": "睾丸女性化综合征"}], "sentences": [{"sentence": "The \"feminisation\" of alcohol has been going on for years, from the prancing fawns of Babycham in the 1950s through lurid-hued alcopops to today's handbag-sized bottles and cartons of wine.", "translation": "这种“女性化”的酒精饮品已流行多年，从20世纪50年代盛行的杯杯香到火红色调的酒精软饮料，到今天的手提包大小的瓶装和盒装的葡萄酒。"}]}