{"word": "fillip", "headword": "fillip", "frequency": "69", "list": "15k", "usPhone": "ˈfɪlɪp", "ukPhone": "ˈfɪlɪp", "examType": [], "translations": ["n.刺激；弹指", "vt.用指弹", "vi.弹指"], "phrs": [{"headword": "fillip", "key-speech": "fillip", "translation": "弹指, 刺激, 刺激品, 轻击"}, {"headword": "Not Worth A Fillip", "key-speech": "Not+Worth+A+Fillip", "translation": "毫不足取"}, {"headword": "Fillip The Rabbits", "key-speech": "Fillip+The+Rabbits", "translation": "指头弹兔子"}, {"headword": "C Fillip", "key-speech": "C+Fillip", "translation": "标签"}, {"headword": "Fillip Matejicek", "key-speech": "Fillip+Matejicek", "translation": "简约书籍设计"}, {"headword": "Fillip C", "key-speech": "Fillip+C", "translation": "名称"}, {"headword": "Fillip B", "key-speech": "Fillip+B", "translation": "名称"}, {"headword": "Fillip Massage", "key-speech": "Fillip+Massage", "translation": "弹指按摩"}, {"headword": "fillip dimitrov", "key-speech": "fillip+dimitrov", "translation": "菲利普迪米特罗夫"}], "sentences": [{"sentence": "The news gave a fillip to the telecommunications sector.", "translation": "这个消息给电信部门注了一剂强心针。"}, {"sentence": "A drop in interest rates gave a welcome fillip to the housing market.", "translation": "降低利率给房屋市场带来利好刺激。"}, {"sentence": "It could also give a fillip to revenues.", "translation": "它也会刺激财政收入。"}]}