{"word": "funnelling", "headword": "funnel", "frequency": "18", "list": "7k", "usPhone": "ˈfʌnlɪŋ", "ukPhone": "", "examType": [], "translations": ["n.漏斗作用；[气象] 狭管效应"], "phrs": [{"headword": "funnelling", "key-speech": "funnelling", "translation": "狭管效应, 是什么意思及反义词, 漏斗作用"}, {"headword": "funnelling effect", "key-speech": "funnelling+effect", "translation": "漏斗效应"}, {"headword": "Funnelling Technique", "key-speech": "Funnelling+Technique", "translation": "狭管筛选技术"}], "sentences": [{"sentence": "Wind was funnelling through the gorge.", "translation": "风吹过峡谷。"}, {"sentence": "The winds came from the north, across the plains, funnelling down the valley.", "translation": "风从北方吹来，刮过平原，穿过山谷。"}, {"sentence": "Mr Osborne is funnelling some money into science and apprenticeships.", "translation": "奥斯本先生正把一些资金投放于科学和学徒制。"}]}