{"word": "glutaraldehyde", "headword": "glutaraldehyde", "frequency": "26", "list": "20k", "usPhone": "ˌɡluːtəˈrældəˌhaɪd", "ukPhone": "ˌɡluːtəˈrældɪˌhaɪd", "translations": ["[有化] 戊二醛"], "phrs": [], "sentences": [{"sentence": "Physiological property of glutaraldehyde was briefed.", "translation": "简述了戊二醛生理性质。"}, {"sentence": "Objective To compare and evaluate effect of medication of the root canal with glutaraldehyde .", "translation": "目的对比和评价戊二醛用于根管消毒的临床效果。"}, {"sentence": "Dehydration behavior of polyvinyl alcohol glutaraldehyde hydrogel has been investigated in this paper.", "translation": "本文对聚乙烯醇-戊二醛水凝胶的脱水行为进行了研究。"}]}