{"word": "horrid", "headword": "horrid", "frequency": "220", "list": "9k", "usPhone": "ˈhɔːrɪd", "ukPhone": "ˈhɒrɪd", "translations": ["可怕的；恐怖的；极讨厌的"], "phrs": [], "sentences": [{"sentence": "It's a horrid experience and I wouldn't wish it on my worst enemy.", "translation": "这是一次可怕的经历，我甚至不希望它发生在我仇敌的身上。"}, {"sentence": "In a horrid silence, Mrs. Darling smelt the bowl.", "translation": "达琳太太在可怕的沉默中闻了闻那只碗。"}, {"sentence": "When she brought her picture-book, he asked, \"What horrid beasts have you there?\"", "translation": "当她拿来画册时，他问道：“你画的是什么可怕的野兽？”"}]}