{"word": "leeches", "headword": "leech", "frequency": "68", "list": "11k", "usPhone": "ˈliːtʃɪz", "ukPhone": "ˈliːtʃɪz", "translations": ["蛭类（leech 的复数）", "用水蛭吸……的血（leech 的三单形式）"], "phrs": [], "sentences": [{"sentence": "They're just a bunch of leeches living off others!", "translation": "他们只不过是一帮靠别人生活的寄生虫！"}, {"sentence": "A genuinely comprehensive medical practice does not have to include leeches, the eye of newt, or dragon dung.", "translation": "真正全面的医学实践并不一定要包括水蛭、蝾螈之眼或龙粪。"}, {"sentence": "Farmers are not leeches on society.", "translation": "农民不是水蛭对社会的影响。"}]}