{"word": "miscalculate", "headword": "calculate", "frequency": "4", "list": "2k", "usPhone": "ˌmɪsˈkælkjuleɪt", "ukPhone": "ˌmɪsˈkælkjuleɪt", "translations": ["算错；估计错误", "算错；判断错误"], "phrs": [], "sentences": [{"sentence": "The second is that the Germans miscalculate.", "translation": "其二就是德国人判断错误。"}, {"sentence": "Sooner or later, one side or the other would miscalculate.", "translation": "或早或晚，终有一方会做出错误的估计。"}, {"sentence": "But Goldman appeared to miscalculate how serious and how long the crisis would be.", "translation": "不过，高盛似乎错误估算了危机的严重程度和持续时间。"}]}