{"word": "mortgaged", "headword": "mortgage", "frequency": "78", "list": "3k", "usPhone": "", "ukPhone": "", "examType": ["CET4", "CET6", "考研", "TOEFL", "GRE", "GMAT", "商务英语"], "translations": ["adj．抵押的：已经作为抵押品的，用于表示财产或资产已经被用作抵押贷款的担保。", "· The house is mortgaged to the bank.", "这房子已抵押给银行。"], "phrs": [{"headword": "housing mortgage", "translation": "住房按揭"}, {"headword": "mortgage loan", "translation": "按揭贷款；抵押借款"}, {"headword": "subprime mortgage", "translation": "次级房贷"}, {"headword": "mortgage market", "translation": "抵押信贷市场"}, {"headword": "home mortgage", "translation": "住房抵押"}, {"headword": "housing mortgage loan", "translation": "住房抵押贷款"}, {"headword": "subprime mortgage crisis", "translation": "次贷危机"}, {"headword": "mortgage lending", "translation": "抵押贷款；按揭贷款"}, {"headword": "mortgage lender", "translation": "抵押放贷者"}, {"headword": "chattel mortgage", "translation": "n. 动产抵押"}, {"headword": "mortgage bankers association", "translation": "抵押贷款银行家协会"}, {"headword": "mortgage debt", "translation": "抵押债券"}, {"headword": "residential mortgage", "translation": "住宅抵押借款"}, {"headword": "reverse mortgage", "translation": "反向抵押贷款；反向抵押；反向贷款；倒按揭"}, {"headword": "mortgage bank", "translation": "抵押银行"}, {"headword": "mortgage assets", "translation": "抵押资产"}, {"headword": "second mortgage", "translation": "第二抵押权"}, {"headword": "first mortgage", "translation": "第一抵押权"}, {"headword": "mortgage banking", "translation": "银行抵押业务"}, {"headword": "mortgage credit", "translation": "抵押贷款"}], "sentences": [{"sentence": "We're mortgaged up to the hilt.", "translation": "我们已经把什么都抵押了。"}, {"sentence": "Two-thirds of householders in this state live in a mortgaged home.", "translation": "该国2/3的屋主住在抵押贷款买来的房子里。"}, {"sentence": "The house is mortgaged to the bank for twenty thousand dollars.", "translation": "这房子以两万美元押给银行。"}]}