{"word": "objection", "headword": "objected", "frequency": "1324", "list": "3k", "usPhone": "əbˈdʒekʃ(ə)n", "ukPhone": "əbˈdʒekʃ(ə)n", "examType": ["CET4", "CET6", "考研", "IELTS", "GRE", "GMAT"], "translations": ["n.反对的理由；反对，异议；抗议（律师在审判中提出异议的插话）；恼火，烦心；缺点，缺陷；妨碍，障碍"], "phrs": [{"headword": "objection", "key-speech": "objection", "translation": "反对, 异议, 不喜欢, 我抗议"}, {"headword": "objection to", "key-speech": "objection+to", "translation": "接动名词, 阻挡"}, {"headword": "objection to sth", "key-speech": "objection+to+sth", "translation": "反对, 阻挡"}, {"headword": "to raise an objection", "key-speech": "to+raise+an+objection", "translation": "提出异议"}, {"headword": "objection to execution", "key-speech": "objection+to+execution", "translation": "执行异议"}, {"headword": "no objection", "key-speech": "no+objection", "translation": "不反对, 无异议, 取得世行批准, 得到世行批准"}, {"headword": "Objection Handling", "key-speech": "Objection+Handling", "translation": "异议处理, 处理拒绝状况, 障碍处理"}, {"headword": "an objection to", "key-speech": "an+objection+to", "translation": "反对"}, {"headword": "no objection to occupation", "key-speech": "no+objection+to+occupation", "translation": "不反对占用"}], "sentences": [{"sentence": "I have no objection to your request.", "translation": "我不反对你的请求。"}, {"sentence": "His objection was ruled out of order.", "translation": "他的反对被裁定为违反会议规则。"}, {"sentence": "I have no objection to banks making money.", "translation": "我对银行赚钱没有反对意见。"}]}