{"word": "phytoestrogens", "headword": "phytoestrogen", "frequency": "0", "list": "20k", "usPhone": "", "ukPhone": "", "examType": [], "translations": ["n.植物雌激素（phytoestrogen 的复数）"], "phrs": [{"headword": "Phytoestrogens", "key-speech": "Phytoestrogens", "translation": "植物雌激素, 激素"}, {"headword": "Which Themselves Contain Phytoestrogens", "key-speech": "Which+Themselves+Contain+Phytoestrogens", "translation": "它们本身含有"}], "sentences": [{"sentence": "This product contains naturally occurring phytoestrogens.", "translation": "本产品含有天然植物雌激素。"}, {"sentence": "Beer is also rich in phytoestrogens, plant versions of oestrogen, which keep bones healthy.", "translation": "啤酒中还富含植物性雌激素，这类植物型的雌激素有助于保持骨骼健康。"}, {"sentence": "So there are foods naturally rich in phytoestrogens that may help keep skin nice and supple.", "translation": "所以有些食物富含植物雌激素可以帮助皮肤保持美丽和弹性。"}]}