{"word": "pocketful", "headword": "pocket", "frequency": "13", "list": "2k", "usPhone": "ˈpɑːkɪtfʊl", "ukPhone": "ˈpɒkɪtfʊl", "examType": [], "translations": ["n.一袋之量；满袋"], "phrs": [{"headword": "pocketful", "key-speech": "pocketful", "translation": "满袋, 一袋之量"}, {"headword": "Pocketful Of Sunshine", "key-speech": "Pocketful+Of+Sunshine", "translation": "满载希望, 阳光满载, 娜塔莎"}, {"headword": "Pocketful Of Music", "key-speech": "Pocketful+Of+Music", "translation": "陈秋霞"}, {"headword": "Pocketful of Miracles", "key-speech": "Pocketful+of+Miracles", "translation": "锦囊妙计, 锦囊, 富贵满华堂"}, {"headword": "Pocketful of rainbows", "key-speech": "Pocketful+of+rainbows", "translation": "满袋彩虹"}, {"headword": "Pocketful of Stars", "key-speech": "Pocketful+of+Stars", "translation": "月下星河"}, {"headword": "Pocketful of rain baing", "key-speech": "Pocketful+of+rain+baing", "translation": "雨衣的口袋"}, {"headword": "A Pocketful of Rye", "key-speech": "A+Pocketful+of+Rye", "translation": "黑麦奇案, 原名"}, {"headword": "A Pocketful of Mirac-les", "key-speech": "A+Pocketful+of+Mirac-les", "translation": "一口袋奇迹"}, {"headword": "A pocketful of money", "key-speech": "A+pocketful+of+money", "translation": "整袋钱币"}], "sentences": [{"sentence": "I got a pocket, got a pocketful of sunshine.", "translation": "我有个口袋，装着满满的阳光。"}, {"sentence": "Most entrepreneurs have a pocketful of ideas, many of them viable.", "translation": "多数创业家都有一大堆的创意，其中许多都是可行的。"}, {"sentence": "The headgear weighs just 1.6 ounces, about as much as a pocketful of change.", "translation": "整个帽子仅重0.045千克，差不多相当于一口袋零钱的重量。"}]}