{"word": "prescription", "headword": "prescription", "frequency": "677", "list": "4k", "usPhone": "prɪˈskrɪpʃ(ə)n", "ukPhone": "prɪˈskrɪpʃn", "examType": ["高中", "CET4", "CET6", "考研", "IELTS", "TOEFL", "GRE", "GMAT", "SAT"], "translations": ["n.处方，药方；处方药；开处方，开药方；<正式>解决方法，诀窍；<法律>取得的时效（根据长期或不确定时期持续使用或以长期习惯为基础确立的要求权）（=positive prescription)）", "adj.凭处方方可购买的"], "phrs": [{"headword": "folk prescription", "translation": "偏方；民间药方"}, {"headword": "prescription drug", "translation": "须医师处方才可买的药品"}, {"headword": "exercise prescription", "translation": "运动处方"}, {"headword": "prescription medicine", "translation": "处方药"}, {"headword": "on prescription", "translation": "凭处方(的)，根据药方(的)"}, {"headword": "make up a prescription", "translation": "配药，调剂"}, {"headword": "negative prescription", "translation": "【法律】(请求权的)消除时效"}], "sentences": [{"sentence": "Nicola got her prescription for strep.", "translation": "妮古拉拿了治疗链球菌性咽喉炎的处方药。"}, {"sentence": "The pharmacist will make up your prescription.", "translation": "药剂师会给你依处方配药。"}, {"sentence": "They are not available without a prescription.", "translation": "这些药没有处方不能出售。"}]}