{"word": "progressively", "headword": "progress", "frequency": "765", "list": "2k", "usPhone": "prəˈɡresɪvli", "ukPhone": "prəˈɡresɪvli", "translations": ["渐进地；日益增多地"], "phrs": [], "sentences": [{"sentence": "Her symptoms became progressively worse.", "translation": "她的症状逐步恶化。"}, {"sentence": "The relative proportion of different species of animals hunted by people in the region also changed progressively.", "translation": "该地区被人们猎杀的各种动物的相对比例也在逐步变化。"}, {"sentence": "The pain got progressively worse.", "translation": "疼痛越来越厉害。"}]}