{"word": "proscribed", "headword": "proscribe", "frequency": "98", "list": "10k", "usPhone": "", "ukPhone": "prəˈskraɪbd", "translations": ["宣布禁止；谴责；宣布（某人）为不法之徒（proscribe 的过去式及过去分词）", "禁止的；被谴责的；非法的"], "phrs": [], "sentences": [{"sentence": "In some cultures surgery is proscribed.", "translation": "在有些文化里，外科手术是被禁止的。"}, {"sentence": "Some usages are \"prescribed,\" to be learnt and followed accurately; others are \"proscribed,\" to be avoided.", "translation": "一些被“规定的”用法，要准确地学习和遵循；另一些被“禁止的”用法，则要避免使用。"}, {"sentence": "They are proscribed by federal law from owning guns.", "translation": "根据联邦法律规定，他们不准拥有枪支。"}]}