{"word": "reliably", "headword": "rely", "frequency": "276", "list": "2k", "usPhone": "rɪˈlaɪəbli", "ukPhone": "rɪˈlaɪəbli", "examType": ["GRE"], "translations": ["adv.可靠地；确实地"], "phrs": [{"headword": "reliably", "key-speech": "reliably", "translation": "可靠地"}, {"headword": "work reliably", "key-speech": "work+reliably", "translation": "作业可靠性"}, {"headword": "reliably inferred loading", "key-speech": "reliably+inferred+loading", "translation": "可靠地推断出加载, 可靠推断装载, 可靠推断加载"}, {"headword": "perform reliably", "key-speech": "perform+reliably", "translation": "运行可靠"}, {"headword": "guarantee reliably", "key-speech": "guarantee+reliably", "translation": "可靠地保证"}, {"headword": "reliably excellent", "key-speech": "reliably+excellent", "translation": "非常可靠"}, {"headword": "Reliably Sealing", "key-speech": "Reliably+Sealing", "translation": "密封性好"}, {"headword": "reliably unfailingly", "key-speech": "reliably+unfailingly", "translation": "可靠地"}, {"headword": "stably and reliably", "key-speech": "stably+and+reliably", "translation": "稳定可靠"}, {"headword": "steadily and reliably", "key-speech": "steadily+and+reliably", "translation": "稳定可靠地"}], "sentences": [{"sentence": "The most powerful computers struggle to reliably recognize the shape of an object, the most elementary of tasks for a ten-month-old kid.", "translation": "最强大的计算机都难以可靠地识别出某个物体的形状，而这对于10个月大的孩子来说是最基础的任务。"}, {"sentence": "Economists who study the relationship between money and happiness have consistently found that, above a certain income, the two do not reliably correlate.", "translation": "研究金钱与幸福关系的经济学家们一致发现，在一定的收入之上，两者之间就并没有可靠的关联。"}, {"sentence": "Birds store energy as subcutaneous fat deposits or \"body reserves\"; changes in these reserves can be reliably estimated by measuring changes in body mass.", "translation": "鸟类以皮下脂肪沉积或“身体储备”的形式储存能量；通过测量体重的变化，可以可靠地估计这些储备的变化。"}]}