{"word": "rescues", "headword": "rescue", "frequency": "99", "list": "3k", "usPhone": "ˈreskjuːz", "ukPhone": "", "translations": ["救援；营救（rescue 的复数形式）", "救援（rescue 的第三人称单数形式）；救出"], "phrs": [{"headword": "rescue work", "translation": "n. 救济事业"}, {"headword": "rescue workers", "translation": "救援人员"}, {"headword": "search and rescue", "translation": "搜索与营救"}, {"headword": "rescue operation", "translation": "救护工作，拯救行动；抢险救援工作；救助作业"}, {"headword": "rescue package", "translation": "一揽子救援计划"}, {"headword": "rescue mission", "translation": "营救任务，救助任务；抢险救援任务"}, {"headword": "rescue equipment", "translation": "救援装备；救生设备"}, {"headword": "come to the rescue", "translation": "救援；前来营救"}, {"headword": "rescue vehicle", "translation": "救援车；修理车"}, {"headword": "rescue ship", "translation": "救难船；海难救助船"}, {"headword": "rescue crew", "translation": "救护队"}], "sentences": [{"sentence": "Firemen know how to perform rescues safely.", "translation": "消防队员知道如何安全地进行救援。"}, {"sentence": "Speaking of romance, when Vision rescues Scarlet Witch from the floating city, they slow down and exchange a deep look.", "translation": "提到浪漫，幻视将猩红女巫从浮城中救起时，他们放慢动作，并深深对视了一眼。"}, {"sentence": "He sometimes rescues people.", "translation": "他有时救人。"}]}