{"word": "rhythmically", "headword": "rhythm", "frequency": "128", "list": "3k", "usPhone": "ˈrɪðmɪkli", "ukPhone": "ˈrɪðmɪkli", "translations": ["有节奏地"], "phrs": [], "sentences": [{"sentence": "She stood, swaying her hips, moving rhythmically.", "translation": "她站着，摇摆着臀部，有节奏地动着。"}, {"sentence": "They danced rhythmically, swaying their hips to the music.", "translation": "他们伴着音乐扭动屁股，有节奏地跳舞。"}, {"sentence": "She turns the pebbles over and over, rhythmically, rocking.", "translation": "她将鹅卵石有节奏的一遍一遍地翻转。"}]}