{"word": "tastiest", "headword": "taste", "frequency": "11", "list": "1k", "usPhone": "ˈteɪstiɪst", "ukPhone": "", "translations": ["美味的（tasty 的最高级）"], "phrs": [], "sentences": [{"sentence": "We found the tastiest tapas in the most unprepossessing bars.", "translation": "我们在最其貌不扬的酒吧找到了最好吃的西班牙餐前小吃。"}, {"sentence": "The tastiest foods are packed full of sugars and fats.", "translation": "最有味道的食品是充满着糖和油脂的。"}, {"sentence": "She brought over the tastiest wonton soup my mother had ever eaten.", "translation": "她送来了馄饨，那是我妈妈吃过的最美味的馄饨。"}]}