{"word": "thoughtless", "headword": "think", "frequency": "96", "list": "1k", "usPhone": "ˈθɔːtləs", "ukPhone": "ˈθɔːtləs", "translations": ["轻率的；欠考虑的；考虑不周的；不顾及他人的"], "phrs": [], "sentences": [{"sentence": "It astonishes me (that) he could be so thoughtless.", "translation": "我真没有料到他会如此轻率。"}, {"sentence": "I seem to be in evil case—and all for an innocent and thoughtless pleasantry.", "translation": "我似乎陷入了不幸的境地——而这一切都是出于一种天真而轻率的玩笑。"}, {"sentence": "How very thoughtless. I'll give him a piece of my mind.", "translation": "太欠考虑了。我要狠狠地批评他。"}]}