{"word": "timeliness", "headword": "time", "frequency": "36", "list": "1k", "usPhone": "ˈtaɪmlinəs", "ukPhone": "ˈtaɪmlinəs", "translations": ["及时；时间性；好时机"], "phrs": [], "sentences": [{"sentence": "Timeliness of data must be communicated.", "translation": "数据及时性必须交流。"}, {"sentence": "Timeliness extends to shipping policies, too.", "translation": "时效性就涉及到了运输政策。"}, {"sentence": "The advantage of citizen reporters in unexpected incidents is their timeliness.", "translation": "突发事件中\"全民记者\"的优势体现在发布新闻的及时性上。"}]}