{"word": "tinkles", "headword": "tinkle", "frequency": "4", "list": "10k", "usPhone": "", "ukPhone": "", "examType": ["GRE"], "translations": ["v．（使）发出清脆的声音：指轻敲、轻击或轻拨等动作发出的清脆声音。", "n．清脆的声音：轻敲、轻击或轻拨等动作发出的清脆声音。"], "phrs": [{"headword": "tinkles", "key-speech": "tinkles", "translation": "动词第三人称单数"}], "sentences": [{"sentence": "Tinkles: Is the puppy alive or not?", "translation": "丁克斯：那只小狗还活着吗？"}, {"sentence": "Tinkles : Is the puppy alive or not?", "translation": "丁克斯：那只小狗还活着吗？"}, {"sentence": "Small drips, tinkles, and bubbles are what birds like.", "translation": "——小水滴、叮当响声和小泡沫才是鸟类所喜欢的。"}]}