{"word": "yourselves", "headword": "you", "frequency": "550", "list": "1k", "usPhone": "jɔːrˈselvz", "ukPhone": "jɔːˈselvz", "translations": ["你自己，你们自己（yourself 的复数）"], "phrs": [{"headword": "for yourself", "translation": "为你自己"}, {"headword": "by yourself", "translation": "独自地，单独地"}, {"headword": "do it yourself", "translation": "自己动手干"}], "sentences": [{"sentence": "Boys and girls, believe in yourselves.", "translation": "孩子们，相信你们自己。"}, {"sentence": "You can try it out for yourselves.", "translation": "你们可以亲自试一试。"}, {"sentence": "I want you to behave yourselves while I'm away.", "translation": "我不在家时你们要乖乖的。"}]}